{
  "parent": "minecraft:recipes/root",
  "rewards": {
    "recipes": [
      "extendedexchange:alchemy/ender_eye_to_chorus_fruit"
    ]
  },
  "criteria": {
    "alchemy_table": {
      "trigger": "minecraft:inventory_changed",
      "conditions": {
        "items": [
          {
            "items": [
              "extendedexchange:alchemy_table"
            ]
          }
        ]
      }
    },
    "has_the_recipe": {
      "trigger": "minecraft:recipe_unlocked",
      "conditions": {
        "recipe": "extendedexchange:alchemy/ender_eye_to_chorus_fruit"
      }
    }
  },
  "requirements": [
    [
      "alchemy_table",
      "has_the_recipe"
    ]
  ]
}